{
  "secretKey": "THISISMYSECURETOKEN",
  "host": "http://localhost",
  "port": "21465",
  "startAllSession": true,
  "tokenStoreType": "redis",
  "webhook": {
    "url": "http://localhost:8080/metazap/api",
    "autoDownload": true,
    "uploadS3": true,
    "readMessage": true,
    "allUnreadOnStart": false
  },
  "archive": {
    "enable": true,
    "waitTime": 10,
    "daysToArchive": 45
  },
  "log": {
    "level": "error",
    "logger": ["console", "file"]
  },
  "createOptions": {
    "browserArgs": [
      "--disable-web-security",
      "--no-sandbox",
      "--disable-web-security",
      "--aggressive-cache-discard",
      "--disable-cache",
      "--disable-application-cache",
      "--disable-offline-load-stale-cache",
      "--disk-cache-size=0",
      "--disable-background-networking",
      "--disable-default-apps",
      "--disable-extensions",
      "--disable-sync",
      "--disable-translate",
      "--hide-scrollbars",
      "--metrics-recording-only",
      "--mute-audio",
      "--no-first-run",
      "--safebrowsing-disable-auto-update",
      "--ignore-certificate-errors",
      "--ignore-ssl-errors",
      "--ignore-certificate-errors-spki-list"
    ]
  },
  "mapper": {
    "enable": true,
    "prefix": "tagone-"
  },
  "db": {
    "mongodbDatabase": "tokens",
    "mongodbCollection": "",
    "mongodbUser": null,
    "mongodbPassword": null,
    "mongodbHost": "localhost",
    "mongodbPort": 27017,
    "redisHost": "redis-10066.c276.us-east-1-2.ec2.cloud.redislabs.com",
    "redisPort": 10066,
    "redisPassword": "vE3Kx7tuBq5bWEBYLH2ReCWSxOqU4o9Q",
    "redisDb": 0
  },
  "awsS3": {
    "awsAccessKeyId": "AKIA5ICCOOZVE5D4CIPG",
    "awsSecretAccessKey": "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",
    "awsDefaultRegion": "us-east-1",
    "awsBucket": "bucketuploadjg"
  }
}
